LICENSE
README.md
setup.py
bin/get_test_jwt_token
bin/pym_monitor
bin/pymconfig
bin/pymdeploy
bin/pymtest
bin/pymversion
pymacaron/__init__.py
pymacaron/api.py
pymacaron/apiloader.py
pymacaron/auth.py
pymacaron/config.py
pymacaron/crash.py
pymacaron/crash.yaml
pymacaron/endpoint.py
pymacaron/exceptions.py
pymacaron/gunicorn.py
pymacaron/log.py
pymacaron/model.py
pymacaron/monitor.py
pymacaron/ping.yaml
pymacaron/resources.py
pymacaron/test.py
pymacaron/utils.py
pymacaron.egg-info/PKG-INFO
pymacaron.egg-info/SOURCES.txt
pymacaron.egg-info/dependency_links.txt
pymacaron.egg-info/not-zip-safe
pymacaron.egg-info/requires.txt
pymacaron.egg-info/top_level.txt
test/test_crash_handler.py
test/test_pep8.py
test/test_ping_api.py
test/testserver.py