Metadata-Version: 2.1
Name: pymacaron
Version: 2.0.316
Summary: REST microservice framework based on Flask, OpenAPI, gunicorn and celery, deployable towards GKE and Beanstalk
Home-page: https://github.com/pymacaron/pymacaron
Author: Erwan Lemonnier
Author-email: erwan@lemonnier.se
License: BSD
Platform: any
Classifier: Environment :: Web Environment
Classifier: Intended Audience :: Developers
Classifier: License :: OSI Approved :: BSD License
Classifier: Operating System :: OS Independent
Classifier: Programming Language :: Python
Classifier: Topic :: Internet :: WWW/HTTP :: Dynamic Content
Classifier: Topic :: Software Development :: Libraries :: Python Modules
Requires-Python: >=3.8
License-File: LICENSE
